Workbook
Name BalanceSheetData: 'Raw Data'!$F$1:$I$8
Name CashFlowData: 'Raw Data'!$K$1:$N$7
Name IncomeStatementData: 'Raw Data'!$A$1:$D$8

Sheet Summary
A1: Summary of Findings: Costco Financial Statements 2023-2025
A4: Revenue increased over the 3 year period, indicating consistent growth in demand and strong warehouse performance. Commentary in the source documents mentions that the company opens new warehouses each year, which increases upfront costs but supports long-term revenue growth.
A5: Cost of goods sold also increased over the period, resulting in net income/profit margins growing more slowly than revenue. Rising costs are potentially due to inflation, increases in tarriffs and other taxes and fees, supply chain disruptions, and broader cost structure changes.
A6: Operating cash flow increased by nearly 18% from 2024 to 2025, reflecting strong cash inflow from core operations.
A7: Growth has been financed more through equity and retained earnings rather than debt over time. This indicates a relatively strong financial position.
A8: Membership revenue has gradually increased - management commentary mentions price increases and new member sign-ups as the reason.
A9: Management highlights in-warehouse merchandise and ancillary sales as key performance drivers. Memberships come with no operational costs but consistently represent less than 2% of total revenue.
A10: Overall, the company demonstrated consistent revenue growth, strong cash flow, and operational improvement over the period. Despite revenue growth, profitability grew only slightly, perhaps due to increasing cost pressures or tight operational margins.

Sheet Income Statement
A1: Income Statement: Vertical Analysis Over Three Years
A5: $ in millions
B6: 2023 | C6: 2024 | D6: 2025 | F6: 2023 | G6: 2024 | H6: 2025
A7: Net sales revenue | B7: =VLOOKUP(A7, IncomeStatementData, 4, FALSE) -> 237710 | C7: =VLOOKUP(A7, IncomeStatementData, 3, FALSE) -> 249625 | D7: =VLOOKUP(A7, IncomeStatementData, 2, FALSE) -> 269912 | F7: =B7/B9 -> 0.98109703 | G7: =C7/C9 -> 0.98102597 | H7: =D7/D9 -> 0.98066016
A8: Membership fees | B8: =VLOOKUP(A8, IncomeStatementData, 4, FALSE) -> 4580 | C8: =VLOOKUP(A8, IncomeStatementData, 3, FALSE) -> 4828 | D8: =VLOOKUP(A8, IncomeStatementData, 2, FALSE) -> 5323 | F8: =B8/B9 -> 0.018902968 | G8: =C8/C9 -> 0.018974034 | H8: =D8/D9 -> 0.019339837
A9: Total revenue | B9: =VLOOKUP(A9, IncomeStatementData, 4, FALSE) -> 242290 | C9: =VLOOKUP(A9, IncomeStatementData, 3, FALSE) -> 254453 | D9: =VLOOKUP(A9, IncomeStatementData, 2, FALSE) -> 275235 | F9: 1 | G9: 1 | H9: 1
A11: COGS | B11: =VLOOKUP(A11, IncomeStatementData, 4, FALSE) -> 212586 | C11: =VLOOKUP(A11, IncomeStatementData, 3, FALSE) -> 222358 | D11: =VLOOKUP(A11, IncomeStatementData, 2, FALSE) -> 239886 | F11: =B11/B9 -> 0.87740311 | G11: =C11/C9 -> 0.87386669 | H11: =D11/D9 -> 0.87156793
A12: Gross profit | B12: =B9-B11 -> 29704 | C12: =C9-C11 -> 32095 | D12: =D9-D11 -> 35349 | F12: =B12/B9 -> 0.12259689 | G12: =C12/C9 -> 0.12613331 | H12: =D12/D9 -> 0.12843207
A13: Operating expenses | B13: =VLOOKUP(A13, IncomeStatementData, 4, FALSE) -> 21590 | C13: =VLOOKUP(A13, IncomeStatementData, 3, FALSE) -> 22810 | D13: =VLOOKUP(A13, IncomeStatementData, 2, FALSE) -> 24996 | F13: =B13/B9 -> 0.089108094 | G13: =C13/C9 -> 0.089643274 | H13: =D13/D9 -> 0.090816938
A14: Operating income | B14: =VLOOKUP(A14, IncomeStatementData, 4, FALSE) -> 8114 | C14: =VLOOKUP(A14, IncomeStatementData, 3, FALSE) -> 9285 | D14: =VLOOKUP(A14, IncomeStatementData, 2, FALSE) -> 10383 | F14: =B14/B9 -> 0.033488794 | G14: =C14/C9 -> 0.036490039 | H14: =D14/D9 -> 0.037724127
A16: Net income | B16: =VLOOKUP(A16, IncomeStatementData, 4, FALSE) -> 6292 | C16: =VLOOKUP(A16, IncomeStatementData, 3, FALSE) -> 7367 | D16: =VLOOKUP(A16, IncomeStatementData, 2, FALSE) -> 8099 | F16: =B16/B9 -> 0.02596888 | G16: =C16/C9 -> 0.028952302 | H16: =D16/D9 -> 0.029425763

Sheet Balance Sheet
A1: Balance Sheet: Horizontal Analysis Over Three Years
A5: $ in millions | F5: Variance in Dollars | I5: Variance as Percentage
B6: 2023 | C6: 2024 | D6: 2025 | F6: 2023-2024 | G6: 2024-2025 | I6: 2023-2024 | J6: 2024-2025
A7: Cash and cash equivalents | B7: =VLOOKUP(A7, BalanceSheetData, 4, FALSE) -> 13700 | C7: =VLOOKUP(A7, BalanceSheetData, 3, FALSE) -> 9906 | D7: =VLOOKUP(A7, BalanceSheetData, 2, FALSE) -> 14161 | F7: =C7-B7 -> -3794 | G7: =D7-C7 -> 4255 | I7: =F7/B7 -> -0.27693431 | J7: =G7/C7 -> 0.42953765
A8: Merchandise inventories | B8: =VLOOKUP(A8, BalanceSheetData, 4, FALSE) -> 16651 | C8: =VLOOKUP(A8, BalanceSheetData, 3, FALSE) -> 18647 | D8: =VLOOKUP(A8, BalanceSheetData, 2, FALSE) -> 18116 | F8: =C8-B8 -> 1996 | G8: =D8-C8 -> -531 | I8: =F8/B8 -> 0.11987268 | J8: =G8/C8 -> -0.028476431
A9: Total current assets | B9: =VLOOKUP(A9, BalanceSheetData, 4, FALSE) -> 35879 | C9: =VLOOKUP(A9, BalanceSheetData, 3, FALSE) -> 34246 | D9: =VLOOKUP(A9, BalanceSheetData, 2, FALSE) -> 38380 | F9: =C9-B9 -> -1633 | G9: =D9-C9 -> 4134 | I9: =F9/B9 -> -0.045514089 | J9: =G9/C9 -> 0.12071483
A10: Total assets | B10: =VLOOKUP(A10, BalanceSheetData, 4, FALSE) -> 68994 | C10: =VLOOKUP(A10, BalanceSheetData, 3, FALSE) -> 69831 | D10: =VLOOKUP(A10, BalanceSheetData, 2, FALSE) -> 77099 | F10: =C10-B10 -> 837 | G10: =D10-C10 -> 7268 | I10: =F10/B10 -> 0.01213149 | J10: =G10/C10 -> 0.10407985
A12: Total current liabilities | B12: =VLOOKUP(A12, BalanceSheetData, 4, FALSE) -> 33583 | C12: =VLOOKUP(A12, BalanceSheetData, 3, FALSE) -> 35464 | D12: =VLOOKUP(A12, BalanceSheetData, 2, FALSE) -> 37108 | F12: =C12-B12 -> 1881 | G12: =D12-C12 -> 1644 | I12: =F12/B12 -> 0.056010481 | J12: =G12/C12 -> 0.046356869
A13: Total liabilities | B13: =VLOOKUP(A13, BalanceSheetData, 4, FALSE) -> 43936 | C13: =VLOOKUP(A13, BalanceSheetData, 3, FALSE) -> 46209 | D13: =VLOOKUP(A13, BalanceSheetData, 2, FALSE) -> 47935 | F13: =C13-B13 -> 2273 | G13: =D13-C13 -> 1726 | I13: =F13/B13 -> 0.051734341 | J13: =G13/C13 -> 0.037352031
A15: Total equity | B15: =VLOOKUP(A15, BalanceSheetData, 4, FALSE) -> 25058 | C15: =VLOOKUP(A15, BalanceSheetData, 3, FALSE) -> 23622 | D15: =VLOOKUP(A15, BalanceSheetData, 2, FALSE) -> 29164 | F15: =C15-B15 -> -1436 | G15: =D15-C15 -> 5542 | I15: =F15/B15 -> -0.057307048 | J15: =G15/C15 -> 0.2346118

Sheet Cash Flow
A1: Cash Flow: Horizontal Analysis
A5: $ in millions | F5: Variance in Dollars | I5: Variance as Percentage
B6: 2023 | C6: 2024 | D6: 2025 | F6: 2023-2024 | G6: 2024-2025 | I6: 2023-2024 | J6: 2024-2025
A7: Cash from operating activities | B7: =VLOOKUP(A7, CashFlowData, 4, FALSE) -> 11068 | C7: =VLOOKUP(A7, CashFlowData, 3, FALSE) -> 11339 | D7: =VLOOKUP(A7, CashFlowData, 2, FALSE) -> 13335 | F7: =C7-B7 -> 271 | G7: =D7-C7 -> 1996 | I7: =F7/B7 -> 0.024485002 | J7: =G7/C7 -> 0.17602963
A8: Cash from investing activities | B8: =VLOOKUP(A8, CashFlowData, 4, FALSE) -> -4972 | C8: =VLOOKUP(A8, CashFlowData, 3, FALSE) -> -4409 | D8: =VLOOKUP(A8, CashFlowData, 2, FALSE) -> -5311 | F8: =C8-B8 -> 563 | G8: =D8-C8 -> -902 | I8: =F8/B8 -> -0.11323411 | J8: =G8/C8 -> 0.20458154
A9: Cash from financing activities | B9: =VLOOKUP(A9, CashFlowData, 4, FALSE) -> -2614 | C9: =VLOOKUP(A9, CashFlowData, 3, FALSE) -> -10764 | D9: =VLOOKUP(A9, CashFlowData, 2, FALSE) -> -3775 | F9: =C9-B9 -> -8150 | G9: =D9-C9 -> 6989 | I9: =F9/B9 -> 3.1178271 | J9: =G9/C9 -> -0.64929394
A10: Capital expenditure | B10: =VLOOKUP(A10, CashFlowData, 4, FALSE) -> 170 | C10: =VLOOKUP(A10, CashFlowData, 3, FALSE) -> 203 | D10: =VLOOKUP(A10, CashFlowData, 2, FALSE) -> 193 | F10: =C10-B10 -> 33 | G10: =D10-C10 -> -10 | I10: =F10/B10 -> 0.19411765 | J10: =G10/C10 -> -0.049261084
A12: Total cash, beginning of year | B12: =VLOOKUP(A12, CashFlowData, 4, FALSE) -> 10203 | C12: =VLOOKUP(A12, CashFlowData, 3, FALSE) -> 13700 | D12: =VLOOKUP(A12, CashFlowData, 2, FALSE) -> 9906 | F12: =C12-B12 -> 3497 | G12: =D12-C12 -> -3794 | I12: =F12/B12 -> 0.34274233 | J12: =G12/C12 -> -0.27693431
A13: Total cash, end of year | B13: =VLOOKUP(A13, CashFlowData, 4, FALSE) -> 13700 | C13: =VLOOKUP(A13, CashFlowData, 3, FALSE) -> 9906 | D13: =VLOOKUP(A13, CashFlowData, 2, FALSE) -> 14161 | F13: =C13-B13 -> -3794 | G13: =D13-C13 -> 4255 | I13: =F13/B13 -> -0.27693431 | J13: =G13/C13 -> 0.42953765

Sheet Ratios
A1: Business Ratios for 2025 by Type
A5: Liquidity | D5: Leverage
A6: Quick ratio | B6: =('Raw Data'!G2+'Raw Data'!G9+'Raw Data'!G10)/'Raw Data'!G6 -> 0.49819446 | D6: Debt to equity | E6: ='Raw Data'!G7/'Raw Data'!G8 -> 1.643636
A7: Cash ratio | B7: ='Raw Data'!G2/'Raw Data'!G6 -> 0.38161582 | D7: Debt to capital | E7: ='Raw Data'!G7/'Raw Data'!G5 -> 0.6217331
A8: Current ratio | B8: ='Raw Data'!G4/'Raw Data'!G6 -> 1.0342783 | D8: Debt to EBITDA | E8: ='Raw Data'!G7/('Raw Data'!B7+'Raw Data'!L8) -> 3.7422906
A9: Net working capital (millions) | B9: ='Raw Data'!G4-'Raw Data'!G6 -> 1272 | D9: Interest coverage | E9: =ABS('Raw Data'!B7/'Raw Data'!B9) -> 67.422078
A13: Efficiency | D13: Profitability
A14: Inventory turnover | B14: ='Raw Data'!B5/(('Raw Data'!G3+'Raw Data'!H3)/2) -> 13.050404 | D14: Gross profit margin | E14: =('Raw Data'!B2-'Raw Data'!B5)/'Raw Data'!B2 -> 0.11124366
A15: Accounts receivable days | B15: =((('Raw Data'!G10+'Raw Data'!H10)/2)/'Raw Data'!B2)*365 -> 4.0054907 | D15: Net profit margin | E15: ='Raw Data'!B8/'Raw Data'!B2 -> 0.030006076
A16: Accounts payable days | B16: =((('Raw Data'!G11+'Raw Data'!H11)/2)/'Raw Data'!B5)*365 -> 29.825542 | D16: Return on assets | E16: ='Raw Data'!B8/'Raw Data'!G5 -> 0.10504676
A17: Asset turnover | B17: ='Raw Data'!B2/(('Raw Data'!G5+'Raw Data'!H5)/2) -> 3.6740216 | D17: Return on equity | E17: ='Raw Data'!B8/'Raw Data'!G8 -> 0.27770539
A19: Insights
A20: Current ratio slightly above 1 - adequate liquidity
A21: Strong ROE - suggests effective use of equity
A22: Moderate debt-to-equity - some reliance on leverage to support growth
A23: Rapid inventory turnover - efficient use of cash to purchase and sell inventory
A24: Thin profit margins - revenue diverted to costs and expenses

Sheet Charts

Sheet Raw Data
A1: Income Statement | B1: 2025 | C1: 2024 | D1: 2023 | F1: Balance Sheet | G1: 2025 | H1: 2024 | I1: 2023 | K1: Cash Flows Statement | L1: 2025 | M1: 2024 | N1: 2023
A2: Net sales revenue | B2: 269912 | C2: 249625 | D2: 237710 | F2: Cash and cash equivalents | G2: 14161 | H2: 9906 | I2: 13700 | K2: Cash from operating activities | L2: 13335 | M2: 11339 | N2: 11068
A3: Membership fees | B3: 5323 | C3: 4828 | D3: 4580 | F3: Merchandise inventories | G3: 18116 | H3: 18647 | I3: 16651 | K3: Cash from investing activities | L3: -5311 | M3: -4409 | N3: -4972
A4: Total revenue | B4: 275235 | C4: 254453 | D4: 242290 | F4: Total current assets | G4: 38380 | H4: 34246 | I4: 35879 | K4: Cash from financing activities | L4: -3775 | M4: -10764 | N4: -2614
A5: COGS | B5: 239886 | C5: 222358 | D5: 212586 | F5: Total assets | G5: 77099 | H5: 69831 | I5: 68994 | K5: Capital expenditure | L5: 193 | M5: 203 | N5: 170
A6: Operating expenses | B6: 24996 | C6: 22810 | D6: 21590 | F6: Total current liabilities | G6: 37108 | H6: 35464 | I6: 33583 | K6: Total cash, beginning of year | L6: 9906 | M6: 13700 | N6: 10203
A7: Operating income | B7: 10383 | C7: 9285 | D7: 8114 | F7: Total liabilities | G7: 47935 | H7: 46209 | I7: 43936 | K7: Total cash, end of year | L7: 14161 | M7: 9906 | N7: 13700
A8: Net income | B8: 8099 | C8: 7367 | D8: 6292 | F8: Total equity | G8: 29164 | H8: 23622 | I8: 25058 | K8: Depreciation and amortization | L8: 2426
A9: Interest expense | B9: -154 | F9: Short-term investments | G9: 1123
F10: Net accounts receivable | G10: 3203 | H10: 2721
F11: Accounts payable | G11: 19783 | H11: 19421
A12: *All numbers are in millions.
A13: Sources:
A14: Costco 2025 Form 10-K
A15: Costco 2024 Form 10-K
